kzt_exchangerates/__init__.py
kzt_exchangerates/rates.py
python_kzt_exchangerates-0.0.2.dist-info/LICENSE
python_kzt_exchangerates-0.0.2.dist-info/METADATA
python_kzt_exchangerates-0.0.2.dist-info/WHEEL
python_kzt_exchangerates-0.0.2.dist-info/top_level.txt
python_kzt_exchangerates-0.0.2.dist-info/RECORD
