Metadata-Version: 2.1
Name: python-kzt-exchangerates
Version: 0.0.2
Summary: Python library to get exchange rates for Kazakhstani Tenge
Home-page: UNKNOWN
Author: Dastan Abdrakhmanov
Author-email: dastand.climber@gmail.com
License: UNKNOWN
Platform: UNKNOWN
Classifier: Programming Language :: Python :: 3
Classifier: License :: OSI Approved :: MIT License
Classifier: Operating System :: OS Independent
Requires-Python: >=3.5
Requires-Dist: requests
